[
  {
    "FirstName": "Kiarash",
    "LastName": "Alinasab",
    "UserName": "kiarash",
    "Email": "aalinasab@gmail.com"
  },
  {
    "FirstName": "Yaghma",
    "LastName": "Baloochi",
    "UserName": "yaghma",
    "Email": "ebrahimi.yaghma@gmail.com"
  },
  {
    "FirstName": "Mina",
    "LastName": "Torabi",
    "UserName": "minat",
    "Email": "mina.torabi@gmail.com"
  },
  {
    "FirstName": "Mahsa",
    "LastName": "Ghadimi",
    "UserName": "mahsg",
    "Email": "mahsa.ghadimi@gmail.com"
  }
]